cmost/__init__.py
cmost/download.py
cmost/io.py
cmost/lick.py
cmost/processing.py
cmost/assets/index.table
cmost-0.1.1.dist-info/METADATA
cmost-0.1.1.dist-info/WHEEL
cmost-0.1.1.dist-info/top_level.txt
cmost-0.1.1.dist-info/RECORD
