Metadata-Version: 2.4
Name: Cmost
Version: 0.1.1
Summary: A processing tool for FITS files related to LAMOST
Author-email: Yunyu Guo <guoyunyu2017@outlook.com>, Peng Tang <1941275544@qq.com>
License-Expression: Apache-2.0
Classifier: Development Status :: 5 - Production/Stable
Classifier: Intended Audience :: Developers
Classifier: Topic :: Software Development :: Build Tools
Classifier: Programming Language :: Python :: 3.10
Classifier: Programming Language :: Python :: 3.11
Classifier: Programming Language :: Python :: 3.12
Classifier: Programming Language :: Python :: 3.13
Classifier: Programming Language :: Python :: 3.14
Classifier: Operating System :: POSIX :: Linux
Classifier: Operating System :: Microsoft :: Windows
Classifier: Operating System :: MacOS
Requires-Python: >=3.10
Requires-Dist: numpy>=1.23
Requires-Dist: scipy>=1.8
Requires-Dist: astropy>=6.0
